{
  "chapter_info": {
    "class": 7,
    "subject": "Science",
    "chapter_name": "Light: Shadows and Reflections",
    "chapter_number": 11
  },
  "flashcards": [
    { "q": "Define luminous object.", "a": "An object that emits its own light." },
    { "q": "Define non-luminous object.", "a": "An object that does not emit its own light but reflects light from other sources." },
    { "q": "What do we call objects that block light completely?", "a": "Opaque materials or objects." },
    { "q": "What are transparent materials?", "a": "Materials that allow light to pass almost completely through them." },
    { "q": "What are translucent materials?", "a": "Materials that allow light to pass partially through them." },
    { "q": "Define shadow.", "a": "A dark patch formed when light is blocked by an opaque object." },
    { "q": "What is reflection of light?", "a": "The change in direction of light when it strikes a shiny or polished surface." },
    { "q": "What type of mirror forms virtual images?", "a": "A plane mirror forms virtual images." },
    { "q": "Are images in plane mirrors erect or inverted?", "a": "Erect (upright)." },
    { "q": "What is lateral inversion?", "a": "The left-right reversal of an image in a plane mirror." },
    { "q": "Can images formed by plane mirrors be projected on a screen?", "a": "No, they are virtual images." },
    { "q": "Define a pinhole camera.", "a": "A device where light rays from an object pass through a tiny hole and form an image on a screen." },
    { "q": "Are images formed by pinhole cameras erect or inverted?", "a": "Inverted (upside down)." },
    { "q": "Are images in pinhole cameras real or virtual?", "a": "Real images that can be projected on a screen." },
    { "q": "What is a periscope?", "a": "An optical instrument with two plane mirrors used to view objects that are not directly visible." },
    { "q": "How many mirrors does a basic periscope have?", "a": "Two plane mirrors." },
    { "q": "At what angle are mirrors typically positioned in a periscope?", "a": "At 45-degree angles to the vertical." },
    { "q": "What is a kaleidoscope?", "a": "A device with three or more mirrors arranged triangularly with coloured objects inside, creating symmetrical patterns." },
    { "q": "What creates the symmetrical patterns in a kaleidoscope?", "a": "Multiple reflections of coloured objects in the mirrors." },
    { "q": "How many main plane mirrors are in a standard kaleidoscope?", "a": "Three plane mirrors arranged in a triangular prism." },
    { "q": "Name three natural sources of light.", "a": "Sun, stars, and lightning (or fireflies, natural fire)." },
    { "q": "Is the Sun a luminous or non-luminous object?", "a": "Luminous — it emits its own light." },
    { "q": "Is the Moon a luminous or non-luminous object?", "a": "Non-luminous — it reflects light from the Sun." },
    { "q": "Why does the Moon appear bright in the night sky?", "a": "Because it reflects light from the Sun." },
    { "q": "Name three artificial sources of light.", "a": "Electric bulbs, LED lamps, fluorescent tubes (or candles, torches)." },
    { "q": "What do LED lamps consume compared to traditional bulbs?", "a": "Much less power and are brighter and more durable." },
    { "q": "In straight-line. what activity do you see light only when holes are aligned?", "a": "The matchbox activity with holes demonstrates straight-line light propagation." },
    { "q": "Can you see a candle flame through a bent pipe?", "a": "No, because light travels in straight lines and cannot bend around corners." },
    { "q": "What does clear glass allow?", "a": "Light to pass almost completely, making it transparent." },
    { "q": "What does frosted glass allow?", "a": "Light to pass partially, making it translucent." },
    { "q": "What does cardboard allow?", "a": "Light does not pass through, making it opaque." },
    { "q": "Name three requirements for observing a shadow.", "a": "A source of light, an opaque object, and a screen or surface." },
    { "q": "What type of shadow do opaque objects form?", "a": "Dark, sharp shadows." },
    { "q": "What type of shadow do translucent objects form?", "a": "Lighter, softer shadows." },
    { "q": "What does the color of an object determine about its shadow?", "a": "The color of the object does not change the color of its shadow." },
    { "q": "Do all shadows appear the same color?", "a": "Yes, all shadows appear dark regardless of object color." },
    { "q": "What is the image distance from a plane mirror related to?", "a": "The object distance from the mirror — they are equal." },
    { "q": "If you stand 2 meters in front of a mirror, where does your image appear?", "a": "2 meters behind the mirror." },
    { "q": "Is the image in a plane mirror the same size as the object?", "a": "Yes, the image is always the same size as the object." },
    { "q": "When you raise your left arm in a mirror, which arm does the image raise?", "a": "The right arm (due to lateral inversion)." },
    { "q": "How is the word 'AMBULANCE' written on ambulances?", "a": "In reverse (laterally inverted) so it reads correctly in rear-view mirrors." },
    { "q": "What determines the image size in a pinhole camera?", "a": "The distance of the object from the pinhole and the position of the screen." },
    { "q": "Can a pinhole camera form an erect image?", "a": "No, pinhole cameras always form inverted images." },
    { "q": "Does a pinhole camera need a screen to show the image?", "a": "Yes, a pinhole camera requires a screen to display the real image." },
    { "q": "What happens to a pinhole camera image as the object moves farther away?", "a": "The image becomes smaller." },
    { "q": "Why is a pinhole camera image typically smaller than the object?", "a": "Due to the geometry of light rays passing through a point and the distance traveled." },
    { "q": "What is the main principle behind a periscope?", "a": "Using two plane mirrors arranged at 45° angles to redirect light and extend line of sight." },
    { "q": "Why are periscopes used in submarines?", "a": "To see above the water surface without exposing the submarine." },
    { "q": "What type of image do you see through a periscope?", "a": "An erect image of the same size as the object." },
    { "q": "Are periscope images real or virtual?", "a": "Virtual images (formed by plane mirror reflections)." },
    { "q": "Can different patterns be seen in a kaleidoscope?", "a": "Yes, different patterns appear each time the kaleidoscope is turned." },
    { "q": "Who uses kaleidoscopes for design inspiration?", "a": "Designers and artists use them to get ideas for new patterns." },
    { "q": "What is the relationship between light ray angles at a mirror?", "a": "The angle of incidence equals the angle of reflection." },
    { "q": "On what does the sharpness of shadow edges depend?", "a": "The size of the light source and the distance of the object from the screen." },
    { "q": "What is the region of complete darkness in a shadow called?", "a": "Umbra." },
    { "q": "What is the partially illuminated region around a dark shadow called?", "a": "Penumbra." },
    { "q": "Do all transparent objects form shadows?", "a": "Some transparent objects can form very faint shadows due to their edges." },
    { "q": "In which direction does light travel in a uniform medium?", "a": "In straight lines." },
    { "q": "What happens when light strikes a smooth, polished surface?", "a": "It reflects in a definite direction (regular reflection)." },
    { "q": "What happens when light strikes a rough surface?", "a": "It scatters in many directions (diffuse reflection)." },
    { "q": "Name one advantage of LED lamps over traditional bulbs.", "a": "LED lamps consume less power and last longer." },
    { "q": "What type of image cannot be obtained on a screen?", "a": "Virtual images (like those in plane mirrors)." },
    { "q": "What type of image can always be obtained on a screen?", "a": "Real images (like those in pinhole cameras)." },
    { "q": "How many times does light reflect in a basic periscope?", "a": "Two times." },
    { "q": "Is a pinhole camera's image magnified or reduced in size?", "a": "Reduced (smaller than the object)." },
    { "q": "What determines the brightness of the Moon?", "a": "How much sunlight falls on it and is reflected back to Earth." },
    { "q": "Can the Moon produce its own light?", "a": "No, the Moon is non-luminous and relies on reflected sunlight." },
    { "q": "What is the smallest size that makes an effective pinhole?", "a": "Approximately 1-2 mm in diameter." },
    { "q": "What material is commonly used as a screen in a pinhole camera?", "a": "Tracing paper (translucent paper)." },
    { "q": "Does the distance of the light source affect shadow formation?", "a": "Yes, it affects shadow size and sharpness." },
    { "q": "What is the benefit of using a point light source for shadows?", "a": "It produces sharp, well-defined shadow edges." },
    { "q": "In shadow puppetry, what is placed between the light and screen?", "a": "Flat cut-out figures called shadow puppets." },
    { "q": "Which ancient Indian art form uses shadow puppetry?", "a": "Togalu Gombeyaata (Karnataka), Tholu Bommalata (Andhra Pradesh), and other regional forms." },
    { "q": "What should you do with LED lamps at the end of their life?", "a": "Dispose of or recycle them appropriately, not throw them in garbage." },
    { "q": "What type of glass is commonly used in windows?", "a": "Clear glass, which is transparent." },
    { "q": "When is a mirror image called virtual?", "a": "When light rays only appear to come from behind the mirror but don't actually meet." },
    { "q": "Can you see your image in a mirror from any angle?", "a": "Yes, as long as light from you reaches the mirror and reflects to your eyes." },
    { "q": "What is the main difference between a real and virtual image?", "a": "Real images can be projected on a screen; virtual images cannot." },
    { "q": "How many mirrors are needed for a basic periscope design?", "a": "Minimum two plane mirrors." },
    { "q": "What property of mirrors makes kaleidoscopes show multiple images?", "a": "Regular reflection of light by smooth mirror surfaces." },
    { "q": "Why is it important that pinhole camera pinholes are small?", "a": "To allow only direct light rays through, creating a sharp image." },
    { "q": "What happens to an image as you move it farther from a plane mirror?", "a": "The image appears to move farther behind the mirror at the same distance." },
    { "q": "Is it possible to see an object's image without a mirror?", "a": "Yes, by using a pinhole camera or other optical devices that form real images." },
    { "q": "Name the three states of matter through which light can pass.", "a": "Solid, liquid, and gas (in varying degrees depending on material properties)." },
    { "q": "What type of object forms the sharpest shadows?", "a": "Opaque objects with sharp edges under point light sources." },
    { "q": "In a pinhole camera, which end has the pinhole?", "a": "The end facing the object." },
    { "q": "In a pinhole camera, where does the image form?", "a": "On the screen at the opposite end from the pinhole." },
    { "q": "What characterizes a light source as artificial?", "a": "It is created by humans, not occurring naturally (bulbs, lamps, etc.)." },
    { "q": "What is the primary reason mirrors are used instead of windows for reflection?", "a": "Mirrors have highly reflective surfaces that reflect most light; windows are transparent." },
    { "q": "How do you achieve the best focus in a pinhole camera?", "a": "By adjusting the distance between the pinhole and screen." },
    { "q": "What determines how dark a shadow appears?", "a": "How much light is blocked by the object." },
    { "q": "Do shadows have defined edges or blurred edges?", "a": "Both types exist — sharp edges with point light sources, blurred with diffuse light." }
  ]
}
